MANIFEST.in
README.rst
setup.py
catch_turtle/README.txt
catch_turtle/__init__.py
catch_turtle/__main__.py
catch_turtle/button.py
catch_turtle/catch_turtle.py
catch_turtle/cfg.cfg
catch_turtle/turtles.py
catch_turtle.egg-info/PKG-INFO
catch_turtle.egg-info/SOURCES.txt
catch_turtle.egg-info/dependency_links.txt
catch_turtle.egg-info/top_level.txt
catch_turtle/图片/草地.gif
catch_turtle/图片/草地2.gif