Metadata-Version: 1.0
Name: catch-turtle
Version: 1.1
Summary: 使用turtle模块制作的一款游戏。A game that made by using the *turtle* module.作者:七分诚意
Home-page: UNKNOWN
Author: 七分诚意 qq:3076711200 邮箱:3416445406@qq.com
Author-email: 3416445406@qq.com
License: UNKNOWN
Keywords: python,turtle,game
Platform: UNKNOWN
